fio_wrapper/__init__.py
fio_wrapper/base.yml
fio_wrapper/config.py
fio_wrapper/decorator.py
fio_wrapper/endpoints/__init__.py
fio_wrapper/endpoints/abstracts/abstract_building.py
fio_wrapper/endpoints/abstracts/abstract_endpoint.py
fio_wrapper/endpoints/abstracts/abstract_exchange.py
fio_wrapper/endpoints/abstracts/abstract_group.py
fio_wrapper/endpoints/abstracts/abstract_localmarket.py
fio_wrapper/endpoints/abstracts/abstract_material.py
fio_wrapper/endpoints/abstracts/abstract_planet.py
fio_wrapper/endpoints/abstracts/abstract_recipe.py
fio_wrapper/endpoints/abstracts/abstract_sites.py
fio_wrapper/endpoints/abstracts/abstract_storage.py
fio_wrapper/endpoints/endpoints_v1/__init__.py
fio_wrapper/endpoints/endpoints_v1/building.py
fio_wrapper/endpoints/endpoints_v1/exchange.py
fio_wrapper/endpoints/endpoints_v1/group.py
fio_wrapper/endpoints/endpoints_v1/localmarket.py
fio_wrapper/endpoints/endpoints_v1/material.py
fio_wrapper/endpoints/endpoints_v1/planet.py
fio_wrapper/endpoints/endpoints_v1/recipe.py
fio_wrapper/endpoints/endpoints_v1/sites.py
fio_wrapper/endpoints/endpoints_v1/storage.py
fio_wrapper/exceptions.py
fio_wrapper/fio.py
fio_wrapper/fio_adapter.py
fio_wrapper/models/__init__.py
fio_wrapper/models/building_models.py
fio_wrapper/models/exchange_models.py
fio_wrapper/models/group_models.py
fio_wrapper/models/localmarket_models.py
fio_wrapper/models/material_models.py
fio_wrapper/models/planet_models.py
fio_wrapper/models/recipe_models.py
fio_wrapper/models/sites_models.py
fio_wrapper/models/storage_models.py
fio_wrapper/urls.py
fio_wrapper/validators.py
fio_wrapper-1.3.6.dist-info/LICENSE
fio_wrapper-1.3.6.dist-info/METADATA
fio_wrapper-1.3.6.dist-info/WHEEL
fio_wrapper-1.3.6.dist-info/RECORD
