Metadata-Version: 2.3
Name: fio-wrapper
Version: 1.3.6
Summary: Python API wrapper for Prosperous Universes community API FIO.
License: MIT
Keywords: fio,prosperous universe,api,wrapper
Author: Jan
Author-email: jplacht+pyfio@gmail.com
Requires-Python: >=3.8,<4.0
Classifier: Intended Audience :: Developers
Classifier: License :: OSI Approved :: MIT License
Classifier: Operating System :: Unix
Classifier: Programming Language :: Python :: 3
Classifier: Programming Language :: Python :: 3.8
Classifier: Programming Language :: Python :: 3.9
Classifier: Programming Language :: Python :: 3.10
Classifier: Programming Language :: Python :: 3.11
Classifier: Programming Language :: Python :: 3.12
Classifier: Programming Language :: Python :: 3.13
Classifier: Topic :: Internet
Classifier: Topic :: Software Development :: Libraries :: Python Modules
Provides-Extra: cache
Requires-Dist: pydantic (>=2.4.2,<3.0.0)
Requires-Dist: pyyaml (>=6.0.1,<7.0.0)
Requires-Dist: requests (>=2.31.0,<3.0.0)
Requires-Dist: requests-cache[cache] (>=1.1.0,<2.0.0) ; extra == "cache"
Project-URL: Documentation, https://prunplanner.github.io/fio_wrapper/
Project-URL: Homepage, https://prunplanner.github.io/fio_wrapper/
Project-URL: Source, https://github.com/prunplanner/fio_wrapper
